find_compiler/__init__.py
find_compiler/find.py
find_compiler/findc.py
find_compiler/output.py
find_compiler/toolchain/__init__.py
find_compiler/toolchain/detect.py
find_compiler/toolchain/loader.py
find_compiler/toolchain/printer.py
find_compiler/toolchain/matcher/__init__.py
find_compiler/toolchain/matcher/applellvm/__init__.py
find_compiler/toolchain/matcher/clang/__init__.py
find_compiler/toolchain/matcher/clangc2/__init__.py
find_compiler/toolchain/matcher/gcc/__init__.py
find_compiler/toolchain/matcher/msvc/__init__.py
find_compiler-0.0.5.dist-info/LICENSE.txt
find_compiler-0.0.5.dist-info/METADATA
find_compiler-0.0.5.dist-info/RECORD
find_compiler-0.0.5.dist-info/WHEEL
find_compiler-0.0.5.dist-info/entry_points.txt
find_compiler-0.0.5.dist-info/top_level.txt
